{
  "_class": "shapeGroup",
  "booleanOperation": 0,
  "clippingMaskMode": 0,
  "do_objectID": "80CA56AE-93DB-4A6E-B361-C063A5652A69",
  "exportOptions": {
    "_class": "exportOptions",
    "exportFormats": [
    ],
    "includedLayerIds": [
    ],
    "layerOptions": 0,
    "shouldTrim": false
  },
  "frame": {
    "_class": "rect",
    "constrainProportions": false,
    "do_objectID": "0DF39F2C-AE61-44A5-8AFB-2E8787A50410",
    "height": 27,
    "width": 24,
    "x": 4,
    "y": 2
  },
  "hasClickThrough": false,
  "hasClippingMask": false,
  "isFixedToViewport": false,
  "isFlippedHorizontal": false,
  "isFlippedVertical": false,
  "isLocked": false,
  "isVisible": false,
  "layerListExpandedType": 1,
  "layers": [
    {
      "class": "shapePath",
      "id": "1BA82E2A-3C7B-4A98-A603-E03393EBB4C1"
    },
    {
      "class": "shapePath",
      "id": "DF20717F-88E7-43C9-A4B3-7D5CA7CB4913"
    }
  ],
  "name": "icons/icon_32/icon_app_neteasemus",
  "nameIsFixed": true,
  "resizingConstraint": 63,
  "resizingType": 0,
  "rotation": 0,
  "shouldBreakMaskChain": false,
  "style": {
    "_class": "style",
    "blur": {
      "_class": "blur",
      "center": "{0.5, 0.5}",
      "do_objectID": "6C8EF084-9D7A-4AE5-8330-3F15C84EA925",
      "isEnabled": false,
      "motionAngle": 0,
      "radius": 0.2953098845532842,
      "type": 0
    },
    "do_objectID": "ABE606AA-FB69-40F1-8795-621A518BBC6E",
    "endMarkerType": 0,
    "fills": [
      {
        "_class": "fill",
        "color": {
          "_class": "color",
          "alpha": 1,
          "blue": 1,
          "green": 1,
          "red": 1
        },
        "fillType": 0,
        "isEnabled": true,
        "noiseIndex": 0,
        "noiseIntensity": 0,
        "patternFillType": 1,
        "patternTileScale": 1
      }
    ],
    "miterLimit": 10,
    "startMarkerType": 0,
    "windingRule": 0
  },
  "windingRule": 0
}